pydracula-0.2.0.post1.dist-info/METADATA
pydracula-0.2.0.post1.dist-info/WHEEL
pydracula/__init__.py
pydracula/pydracula.abi3.so
pydracula-0.2.0.post1.dist-info/RECORD
