Metadata-Version: 2.1
Name: pydracula
Version: 0.2.0.post1
Summary: 🧛 Count-ing lines, AH AH AHH!
Author: Swarnim Arun <swarnim@deepsource.io>
Author-email: Swarnim Arun <swarnim@deepsource.io>
